nasa/__init__.py
nasa/daemon.py
nasa-0.0.1.dist-info/METADATA
nasa-0.0.1.dist-info/WHEEL
nasa-0.0.1.dist-info/entry_points.txt
nasa-0.0.1.dist-info/top_level.txt
nasa-0.0.1.dist-info/RECORD
