Metadata-Version: 2.1
Name: nasa
Version: 0.0.1
Summary: Network Attached Storage Agent
Home-page: https://github.com/dimchat/
Author: Albert Moky
Author-email: albert.moky@gmail.com
License: MIT
Platform: UNKNOWN
Classifier: Programming Language :: Python :: 3
Classifier: License :: OSI Approved :: MIT License
Classifier: Operating System :: OS Independent
Requires-Dist: stun (>=0.1.4)
Requires-Dist: dmtp (>=0.1.2)
Requires-Dist: dimsdk (>=0.4.3)
